startflask/__init__.py
startflask/startflask.py
startflask/__pycache__/__init__.cpython-37.pyc
startflask/__pycache__/startflask.cpython-37.pyc
startflask/boilerplate/run.py
startflask/boilerplate/app/__init__.py
startflask/boilerplate/app/config.py
startflask/boilerplate/app/models.py
startflask/boilerplate/app/auth/__init__.py
startflask/boilerplate/app/auth/auth.py
startflask/boilerplate/app/auth/templates/auth/login.html
startflask/boilerplate/app/auth/templates/auth/signup.html
startflask/boilerplate/app/main/__init__.py
startflask/boilerplate/app/main/main.py
startflask/boilerplate/app/main/templates/main/dashboard.html
startflask/boilerplate/app/static/style.css
startflask/boilerplate/app/templates/base.html
startflask-0.10.dist-info/LICENSE.txt
startflask-0.10.dist-info/METADATA
startflask-0.10.dist-info/WHEEL
startflask-0.10.dist-info/entry_points.txt
startflask-0.10.dist-info/top_level.txt
startflask-0.10.dist-info/RECORD
