Metadata-Version: 2.1
Name: startflask
Version: 0.10
Summary: UNKNOWN
Home-page: UNKNOWN
Author: Sashito Mizuki
Author-email: sashito.mizuki@gmail.com
License: MIT
Keywords: Flask,startflask,flask start
Platform: UNKNOWN
Requires-Dist: Click
Requires-Dist: Flask
Requires-Dist: Flask-Migrate
Requires-Dist: Flask-Login
Requires-Dist: Flask-SQLAlchemy
Requires-Dist: psycopg2-binary
Requires-Dist: gunicorn
